[
    {
        "name": "Red Bench",
        "category": "people",
        "price": 10,
        "currency": "USD",
        "image": {
            "src": "pexels/pexel1.jpg",
            "alt": ""
        },
        "bestseller": true,
        "featured": false,
        "details": null
    },
    {
        "name": "Egg Balloon",
        "category": "people",
        "price": 15,
        "currency": "USD",
        "image": {
            "src": "pexels/pexel2.jpg",
            "alt": ""
        },
        "bestseller": false,
        "featured": false,
        "details": null
    },
    {
        "name": "Man",
        "category": "people",
        "price": 17,
        "currency": "USD",
        "image": {
            "src": "pexels/pexel3.jpg",
            "alt": ""
        },
        "bestseller": false,
        "featured": false,
        "details": null
    },
    {
        "name": "Architecture",
        "category": "people",
        "price": 18,
        "currency": "USD",
        "dimmentions": {
            "width": 1020,
            "height": 1020
        },
        "image": {
            "src": "pexels/pexel4.jpg",
            "alt": ""
        },
        "bestseller": false,
        "featured": false,
        "details": null
    },
    {
        "name": "Red Bench",
        "category": "people",
        "price": 30,
        "currency": "USD",
        "image": {
            "src": "pexels/pexel5.jpg",
            "alt": ""
        },
        "bestseller": true,
        "featured": false,
        "details": null
    },
    {
        "name": "Egg Balloon",
        "category": "food",
        "price": 40.3,
        "currency": "USD",
        "image": {
            "src": "pexels/pexel6.jpg",
            "alt": ""
        },
        "bestseller": false,
        "featured": false,
        "details": null
    },
    {
        "name": "Man",
        "category": "people",
        "price": 100,
        "currency": "USD",
        "image": {
            "src": "pexels/pexel7.jpg",
            "alt": ""
        },
        "bestseller": false,
        "featured": false,
        "details": null
    },
    {
        "name": "Architecture",
        "category": "landmarks",
        "price": 101,
        "currency": "USD",
        "dimmentions": {
            "width": 1020,
            "height": 1020
        },
        "image": {
            "src": "pexels/pexel8.jpg",
            "alt": ""
        },
        "bestseller": false,
        "featured": false,
        "details": null
    },
    {
        "name": "Red Bench",
        "category": "people",
        "price": 3.89,
        "currency": "USD",
        "image": {
            "src": "pexels/pexel9.jpg",
            "alt": ""
        },
        "bestseller": true,
        "featured": false,
        "details": null
    },
    {
        "name": "Egg Balloon",
        "category": "food",
        "price": 93.89,
        "currency": "USD",
        "image": {
            "src": "pexels/pexel10.jpg",
            "alt": ""
        },
        "bestseller": false,
        "featured": false,
        "details": null
    },
    {
        "name": "Man",
        "category": "people",
        "price": 100,
        "currency": "USD",
        "image": {
            "src": "pexels/pexel11.jpg",
            "alt": ""
        },
        "bestseller": false,
        "featured": false,
        "details": null
    },
    {
        "name": "Architecture",
        "category": "landmarks",
        "price": 101,
        "currency": "USD",
        "dimmentions": {
            "width": 1020,
            "height": 1020
        },
        "image": {
            "src": "pexels/pexel12.jpg",
            "alt": ""
        },
        "bestseller": false,
        "featured": false,
        "details": null
    },
    {
        "name": "Red Bench",
        "category": "people",
        "price": 3.89,
        "currency": "USD",
        "image": {
            "src": "pexels/pexel13.jpg",
            "alt": ""
        },
        "bestseller": true,
        "featured": false,
        "details": null
    },
    {
        "name": "Egg Balloon",
        "category": "food",
        "price": 93.89,
        "currency": "USD",
        "image": {
            "src": "pexels/pexel14.jpg",
            "alt": ""
        },
        "bestseller": false,
        "featured": false,
        "details": null
    },
    {
        "name": "Man",
        "category": "people",
        "price": 100,
        "currency": "USD",
        "image": {
            "src": "pexels/pexel15.jpg",
            "alt": ""
        },
        "bestseller": false,
        "featured": false,
        "details": null
    },
    {
        "name": "Architecture",
        "category": "landmarks",
        "price": 101,
        "currency": "USD",
        "dimmentions": {
            "width": 1020,
            "height": 1020
        },
        "image": {
            "src": "pexels/pexel16.jpg",
            "alt": ""
        },
        "bestseller": false,
        "featured": false,
        "details": null
    },
    {
        "name": "Red Bench",
        "category": "people",
        "price": 200.89,
        "currency": "USD",
        "image": {
            "src": "pexels/pexel17.jpg",
            "alt": ""
        },
        "bestseller": true,
        "featured": false,
        "details": null
    },
    {
        "name": "Egg Balloon",
        "category": "food",
        "price": 300.89,
        "currency": "USD",
        "image": {
            "src": "pexels/pexel18.jpg",
            "alt": ""
        },
        "bestseller": false,
        "featured": false,
        "details": null
    },
    {
        "name": "Man",
        "category": "people",
        "price": 100,
        "currency": "USD",
        "image": {
            "src": "pexels/pexel19.jpg",
            "alt": ""
        },
        "bestseller": false,
        "featured": false,
        "details": null
    },
    {
        "name": "Architecture",
        "category": "landmarks",
        "price": 101,
        "currency": "USD",
        "dimmentions": {
            "width": 1020,
            "height": 1020
        },
        "image": {
            "src": "pexels/pexel20.jpg",
            "alt": ""
        },
        "bestseller": false,
        "featured": false,
        "details": null
    },
    {
        "name": "Red Bench",
        "category": "people",
        "price": 3.89,
        "currency": "USD",
        "image": {
            "src": "pexels/pexel21.jpg",
            "alt": ""
        },
        "bestseller": true,
        "featured": false,
        "details": null
    },
    {
        "name": "Egg Balloon",
        "category": "food",
        "price": 93.89,
        "currency": "USD",
        "image": {
            "src": "pexels/pexel22.jpg",
            "alt": ""
        },
        "bestseller": false,
        "featured": false,
        "details": null
    },
    {
        "name": "Man",
        "category": "people",
        "price": 100,
        "currency": "USD",
        "image": {
            "src": "pexels/pexel23.jpg",
            "alt": ""
        },
        "bestseller": false,
        "featured": false,
        "details": null
    },
    {
        "name": "Architecture",
        "category": "landmarks",
        "price": 101,
        "currency": "USD",
        "dimmentions": {
            "width": 1020,
            "height": 1020
        },
        "image": {
            "src": "pexels/pexel24.jpg",
            "alt": ""
        },
        "bestseller": false,
        "featured": false,
        "details": null
    },
    {
        "name": "Samurai king Restling",
        "category": "landmarks",
        "price": 101,
        "currency": "USD",
        "image": {
            "src": "pexels/pexel25.jpg",
            "alt": ""
        },
        "bestseller": false,
        "featured": true,
        "details": {
            "dimensions": {
                "width": 1020,
                "height": 1020
            },
            "size": 15000,
            "description": "So how did the classical Latin become so incoherent? According to McClintock, a 15th century typesetter likely",
            "recommendations": [
                {
                    "src": "pexels/pexel11.jpg",
                    "alt": ""
                },
                {
                    "src": "pexels/pexel2.jpg",
                    "alt": ""
                },
                {
                    "src": "pexels/pexel3.jpg",
                    "alt": ""
                }
            ]
        }
    }
]